Workbook

Sheet 📊 DASHBOARD
A1: 📊 ANNUAL BILLING DASHBOARD — FY 2025-26
A2: Business Performance Overview | Sharma Trading Co. | Ghaziabad, UP
B4: 📋 Total Invoices | D4: 💰 Total Revenue | F4: ✅ Collected | H4: ⚡ Outstanding | J4: 📈 Net Profit
B5: 508 | D5: ₹46,52,000 | F5: ₹43,48,000 | H5: ₹3,04,000 | J5: ₹17,75,000
B6: vs LY: +12% | D6: 18% Growth | F6: 93.5% Rate | H6: 6.5% Pending | J6: 38.2% Margin
B8: 📅 Monthly Revenue & Collections | H8: 🏆 Top 10 Customers by Revenue
B9: Month | C9: Revenue (₹) | D9: Collected (₹) | E9: Outstanding (₹) | F9: Profit (₹) | H9: Rank | I9: Customer | J9: Revenue | K9: Collected | L9: Balance | M9: Category
B10: Apr'25 | C10: =Sales_Data!C4 -> 285000 | D10: =Sales_Data!D4 -> 260000 | E10: =Sales_Data!E4 -> 25000 | F10: =Sales_Data!G4 -> 105000 | H10: 🥇 | I10: =Customer_Data!B4 -> NK Construction | J10: =Customer_Data!E4 -> 685000 | K10: =Customer_Data!F4 -> 620000 | L10: =Customer_Data!G4 -> 65000 | M10: =Customer_Data!H4 -> A - Premium
B11: May'25 | C11: =Sales_Data!C5 -> 312000 | D11: =Sales_Data!D5 -> 290000 | E11: =Sales_Data!E5 -> 22000 | F11: =Sales_Data!G5 -> 117000 | H11: 🥈 | I11: =Customer_Data!B5 -> Gupta Electronics | J11: =Customer_Data!E5 -> 542000 | K11: =Customer_Data!F5 -> 542000 | L11: =Customer_Data!G5 -> 0 | M11: =Customer_Data!H5 -> A - Premium
B12: Jun'25 | C12: =Sales_Data!C6 -> 298000 | D12: =Sales_Data!D6 -> 275000 | E12: =Sales_Data!E6 -> 23000 | F12: =Sales_Data!G6 -> 110000 | H12: 🥉 | I12: =Customer_Data!B6 -> Mohd Farhan & Sons | J12: =Customer_Data!E6 -> 428000 | K12: =Customer_Data!F6 -> 385000 | L12: =Customer_Data!G6 -> 43000 | M12: =Customer_Data!H6 -> B - Regular
B13: Jul'25 | C13: =Sales_Data!C7 -> 342000 | D13: =Sales_Data!D7 -> 320000 | E13: =Sales_Data!E7 -> 22000 | F13: =Sales_Data!G7 -> 132000 | H13: 4 | I13: =Customer_Data!B7 -> Infosys BPO Ltd | J13: =Customer_Data!E7 -> 398000 | K13: =Customer_Data!F7 -> 398000 | L13: =Customer_Data!G7 -> 0 | M13: =Customer_Data!H7 -> A - Premium
B14: Aug'25 | C14: =Sales_Data!C8 -> 318000 | D14: =Sales_Data!D8 -> 295000 | E14: =Sales_Data!E8 -> 23000 | F14: =Sales_Data!G8 -> 118000 | H14: 5 | I14: =Customer_Data!B8 -> Sharma Textiles | J14: =Customer_Data!E8 -> 312000 | K14: =Customer_Data!F8 -> 280000 | L14: =Customer_Data!G8 -> 32000 | M14: =Customer_Data!H8 -> B - Regular
B15: Sep'25 | C15: =Sales_Data!C9 -> 385000 | D15: =Sales_Data!D9 -> 360000 | E15: =Sales_Data!E9 -> 25000 | F15: =Sales_Data!G9 -> 150000 | H15: 6 | I15: =Customer_Data!B9 -> Pankaj Auto Parts | J15: =Customer_Data!E9 -> 298000 | K15: =Customer_Data!F9 -> 298000 | L15: =Customer_Data!G9 -> 0 | M15: =Customer_Data!H9 -> B - Regular
B16: Oct'25 | C16: =Sales_Data!C10 -> 420000 | D16: =Sales_Data!D10 -> 395000 | E16: =Sales_Data!E10 -> 25000 | F16: =Sales_Data!G10 -> 162000 | H16: 7 | I16: =Customer_Data!B10 -> Bansal Medicals | J16: =Customer_Data!E10 -> 245000 | K16: =Customer_Data!F10 -> 215000 | L16: =Customer_Data!G10 -> 30000 | M16: =Customer_Data!H10 -> C - Occasional
B17: Nov'25 | C17: =Sales_Data!C11 -> 465000 | D17: =Sales_Data!D11 -> 440000 | E17: =Sales_Data!E11 -> 25000 | F17: =Sales_Data!G11 -> 180000 | H17: 8 | I17: =Customer_Data!B11 -> Jain Hardware | J17: =Customer_Data!E11 -> 218000 | K17: =Customer_Data!F11 -> 218000 | L17: =Customer_Data!G11 -> 0 | M17: =Customer_Data!H11 -> B - Regular
B18: Dec'25 | C18: =Sales_Data!C12 -> 512000 | D18: =Sales_Data!D12 -> 480000 | E18: =Sales_Data!E12 -> 32000 | F18: =Sales_Data!G12 -> 197000 | H18: 9 | I18: =Customer_Data!B12 -> Sunita Fashions | J18: =Customer_Data!E12 -> 185000 | K18: =Customer_Data!F12 -> 150000 | L18: =Customer_Data!G12 -> 35000 | M18: =Customer_Data!H12 -> C - Occasional
B19: Jan'26 | C19: =Sales_Data!C13 -> 398000 | D19: =Sales_Data!D13 -> 370000 | E19: =Sales_Data!E13 -> 28000 | F19: =Sales_Data!G13 -> 153000 | H19: 10 | I19: =Customer_Data!B13 -> Mohan Infrastructure | J19: =Customer_Data!E13 -> 165000 | K19: =Customer_Data!F13 -> 165000 | L19: =Customer_Data!G13 -> 0 | M19: =Customer_Data!H13 -> B - Regular
B20: Feb'26 | C20: =Sales_Data!C14 -> 432000 | D20: =Sales_Data!D14 -> 405000 | E20: =Sales_Data!E14 -> 27000 | F20: =Sales_Data!G14 -> 164000
B21: Mar'26 | C21: =Sales_Data!C15 -> 485000 | D21: =Sales_Data!D15 -> 455000 | E21: =Sales_Data!E15 -> 30000 | F21: =Sales_Data!G15 -> 187000
B22: TOTAL | C22: =SUM(C10:C21) -> 4652000 | D22: =SUM(D10:D21) -> 4345000 | E22: =SUM(E10:E21) -> 307000 | F22: =SUM(F10:F21) -> 1775000
B23: 📊 Key Performance Metrics | F23: 📆 Quarterly Analysis | J23: 📂 Revenue by Invoice Type
B24: Avg Monthly Revenue | C24: =Sales_Data!C16/12 -> 387666.67 | F24: Quarter | G24: Revenue | H24: Profit | I24: Growth | J24: Type | K24: Revenue | L24: Share | M24: Trend
B25: Best Month Revenue | C25: =MAX(Sales_Data!C4:C15) -> 512000 | F25: Q1 (Apr-Jun) | G25: =SUM(Sales_Data!C4:C6) -> 895000 | H25: =SUM(Sales_Data!G4:G6) -> 332000 | I25: Base | J25: GST Invoice | K25: 2150000 | L25: 46.2% | M25: 📈 ↑
B26: Total GST Collected | C26: =Sales_Data!H16 -> 837360 | F26: Q2 (Jul-Sep) | G26: =SUM(Sales_Data!C7:C9) -> 1045000 | H26: =SUM(Sales_Data!G7:G9) -> 400000 | I26: +9.4% | J26: Service Invoice | K26: 1280000 | L26: 27.5% | M26: 📈 ↑
B27: Collection Efficiency | C27: =Sales_Data!D16/Sales_Data!C16 -> 0.93400688 | F27: Q3 (Oct-Dec) | G27: =SUM(Sales_Data!C10:C12) -> 1397000 | H27: =SUM(Sales_Data!G10:G12) -> 539000 | I27: +18.2% | J27: Retail Billing | K27: 680000 | L27: 14.6% | M27: 📊 →
B28: Avg Invoice Value | C28: =Sales_Data!C16/Sales_Data!B16 -> 9157.4803 | F28: Q4 (Jan-Mar) | G28: =SUM(Sales_Data!C13:C15) -> 1315000 | H28: =SUM(Sales_Data!G13:G15) -> 504000 | I28: +4.1% | J28: Simple Invoice | K28: 390000 | L28: 8.4% | M28: 📉 ↓
B29: Total Expenses | C29: =Sales_Data!F16 -> 2877000 | J29: Proforma | K29: 152000 | L29: 3.3% | M29: 📈 ↑
A50: 📌 Dashboard auto-updates from Sales_Data & Customer_Data sheets | FY 2025-26 | Sharma Trading Co.

Sheet Sales_Data
A1: RAW SALES DATA — FY 2025-26
A3: Month | B3: Invoices | C3: Revenue | D3: Collected | E3: Outstanding | F3: Expenses | G3: Profit | H3: GST Collected
A4: Apr 2025 | B4: 32 | C4: 285000 | D4: 260000 | E4: 25000 | F4: 180000 | G4: 105000 | H4: 51300
A5: May 2025 | B5: 35 | C5: 312000 | D5: 290000 | E5: 22000 | F5: 195000 | G5: 117000 | H5: 56160
A6: Jun 2025 | B6: 38 | C6: 298000 | D6: 275000 | E6: 23000 | F6: 188000 | G6: 110000 | H6: 53640
A7: Jul 2025 | B7: 40 | C7: 342000 | D7: 320000 | E7: 22000 | F7: 210000 | G7: 132000 | H7: 61560
A8: Aug 2025 | B8: 36 | C8: 318000 | D8: 295000 | E8: 23000 | F8: 200000 | G8: 118000 | H8: 57240
A9: Sep 2025 | B9: 42 | C9: 385000 | D9: 360000 | E9: 25000 | F9: 235000 | G9: 150000 | H9: 69300
A10: Oct 2025 | B10: 45 | C10: 420000 | D10: 395000 | E10: 25000 | F10: 258000 | G10: 162000 | H10: 75600
A11: Nov 2025 | B11: 48 | C11: 465000 | D11: 440000 | E11: 25000 | F11: 285000 | G11: 180000 | H11: 83700
A12: Dec 2025 | B12: 52 | C12: 512000 | D12: 480000 | E12: 32000 | F12: 315000 | G12: 197000 | H12: 92160
A13: Jan 2026 | B13: 44 | C13: 398000 | D13: 370000 | E13: 28000 | F13: 245000 | G13: 153000 | H13: 71640
A14: Feb 2026 | B14: 46 | C14: 432000 | D14: 405000 | E14: 27000 | F14: 268000 | G14: 164000 | H14: 77760
A15: Mar 2026 | B15: 50 | C15: 485000 | D15: 455000 | E15: 30000 | F15: 298000 | G15: 187000 | H15: 87300
A16: TOTAL FY | B16: =SUM(B4:B15) -> 508 | C16: =SUM(C4:C15) -> 4652000 | D16: =SUM(D4:D15) -> 4345000 | E16: =SUM(E4:E15) -> 307000 | F16: =SUM(F4:F15) -> 2877000 | G16: =SUM(G4:G15) -> 1775000 | H16: =SUM(H4:H15) -> 837360

Sheet Customer_Data
A1: CUSTOMER MASTER — FY 2025-26
A3: S.No | B3: Customer Name | C3: City | D3: Total Orders | E3: Revenue (₹) | F3: Paid (₹) | G3: Balance (₹) | H3: Category
A4: 1 | B4: NK Construction | C4: Delhi | D4: 18 | E4: 685000 | F4: 620000 | G4: =E4-F4 -> 65000 | H4: A - Premium
A5: 2 | B5: Gupta Electronics | C5: Noida | D5: 24 | E5: 542000 | F5: 542000 | G5: =E5-F5 -> 0 | H5: A - Premium
A6: 3 | B6: Mohd Farhan & Sons | C6: Ghaziabad | D6: 15 | E6: 428000 | F6: 385000 | G6: =E6-F6 -> 43000 | H6: B - Regular
A7: 4 | B7: Infosys BPO Ltd | C7: Bengaluru | D7: 12 | E7: 398000 | F7: 398000 | G7: =E7-F7 -> 0 | H7: A - Premium
A8: 5 | B8: Sharma Textiles | C8: Delhi | D8: 20 | E8: 312000 | F8: 280000 | G8: =E8-F8 -> 32000 | H8: B - Regular
A9: 6 | B9: Pankaj Auto Parts | C9: Faridabad | D9: 16 | E9: 298000 | F9: 298000 | G9: =E9-F9 -> 0 | H9: B - Regular
A10: 7 | B10: Bansal Medicals | C10: Lucknow | D10: 10 | E10: 245000 | F10: 215000 | G10: =E10-F10 -> 30000 | H10: C - Occasional
A11: 8 | B11: Jain Hardware | C11: Meerut | D11: 14 | E11: 218000 | F11: 218000 | G11: =E11-F11 -> 0 | H11: B - Regular
A12: 9 | B12: Sunita Fashions | C12: Delhi | D12: 8 | E12: 185000 | F12: 150000 | G12: =E12-F12 -> 35000 | H12: C - Occasional
A13: 10 | B13: Mohan Infrastructure | C13: Gurugram | D13: 6 | E13: 165000 | F13: 165000 | G13: =E13-F13 -> 0 | H13: B - Regular
A14: 11 | B14: Raj Automobiles | C14: Agra | D14: 9 | E14: 142000 | F14: 130000 | G14: =E14-F14 -> 12000 | H14: C - Occasional
A15: 12 | B15: Priya Pharma | C15: Kanpur | D15: 7 | E15: 128000 | F15: 128000 | G15: =E15-F15 -> 0 | H15: C - Occasional
B16: TOTALS | D16: =SUM(D4:D15) -> 159 | E16: =SUM(E4:E15) -> 3746000 | F16: =SUM(F4:F15) -> 3529000 | G16: =SUM(G4:G15) -> 217000
